Testbench/vlsif.v
module master(pclk,presetn,pready,ptransfer,pwrite,psel,penable,paddr,pwdata,prdata,paddr_bus,pwdata_bus,pwrite_bus);
input[31:0]pwdata_bus,paddr_bus;
input pwrite_bus;
input pclk,presetn,pready,ptransfer;
output reg pwrite,psel,penable;
output reg[31:0]paddr,pwdata;
input[31:0]prdata;
 //The first [31:0] describes the width of each register,
 ////while the second [31:0] describes the number of elements (32)

localparam idle = 2'b00;
localparam setup = 2'b01;
localparam access = 2'b10;
reg[1:0]ps,ns;

always@(posedge pclk or negedge presetn)begin //active low reset in apb, also async here
        if(~presetn)
                ps <= idle;
        else
                ps <= ns;
end

always@(*)begin

pwrite = pwrite_bus;
paddr = paddr_bus;
pwdata = pwdata_bus;

ns = ps;
psel = 1'b0;
penable = 1'b0;

        case(ps)

                idle:begin
                        if(ptransfer)
                                ns = setup;
                        else
                                ns = idle;
                end

                setup:begin
                                ns = access;
                                psel = 1'b1;
                end

                access:begin
                psel = 1'b1;
                penable = 1'b1;
                        if(pready == 1 && ptransfer == 0)
                                ns = idle;
                        else if(pready == 1 && ptransfer == 1)
                                ns = setup;
                        else
                                ns = access;
                end

                default: ns = idle;

        endcase
end
endmodule

module slave(input pclk,presetn,pwrite,psel,penable,output pready,input[31:0]pwdata,paddr,output reg[31:0]prdata);
reg[31:0]dataf;
assign pready = 1'b1;
always@(posedge pclk or negedge presetn)begin
        if(~presetn)
                dataf <= 0;
        else begin
                        if(pwrite == 1 && penable == 1 && psel == 1)
                                dataf <= pwdata;
                        else if(pwrite == 0 && penable == 1 && psel == 1)
                                prdata <= dataf;
        end
end
endmodule







//vlsi inputs are the system-bus side
module vlsi(
    input pclk,
    input presetn,
    input ptransfer,
    input pwrite_bus,
    input [31:0] paddr_bus,
    input [31:0] pwdata_bus
            );

 wire psel,penable,pwrite,pready; //slave determined based on paddr so it is not declared as a upper bus signal
 wire [31:0] paddr,pwdata,prdata;



master m1(.pclk(pclk),
          .presetn(presetn),
          .penable(penable),
          .psel(psel),
          .pready(pready),
          .pwrite(pwrite),
          .paddr(paddr),
          .pwdata(pwdata),
          .prdata(prdata),
          .ptransfer(ptransfer),
          .paddr_bus(paddr_bus),
          .pwdata_bus(pwdata_bus),
          .pwrite_bus(pwrite_bus)
          );

slave s1(.pclk(pclk),
         .presetn(presetn),
         .pwrite(pwrite),
         .psel(psel),
         .penable(penable),
         .pready(pready),
         .paddr(paddr),
         .pwdata(pwdata),
         .prdata(prdata)
         );

endmodule

Testbench/DUT.v
module Dut_tb;
reg pclk,presetn,ptransfer,pwrite_bus;
reg[31:0] paddr_bus,pwdata_bus;
vlsi v1(.pclk(pclk),.presetn(presetn),.ptransfer(ptransfer),.pwrite_bus(pwrite_bus),.paddr_bus(paddr_bus),.pwdata_bus(pwdata_bus));
initial pclk = 0;

always 
	#5 pclk = ~pclk;

initial begin 
    $dumpfile("vlsi.vcd");
    $dumpvars(0,Dut_tb);
    ptransfer  = 0;pwrite_bus = 0;paddr_bus  = 0;pwdata_bus = 0 ;   
    
$display("+------+--------+-----------+--------+----------+------+---------+----------+----------+");
$display("| Time | preset | ptransfer | pwrite |  paddr   | psel | penable |  pwdata  |  prdata  |");
$display("+------+--------+-----------+--------+----------+------+---------+----------+----------+");

$monitor("| %4t | %6b | %9b | %6b | %8h | %4b | %7b | %8h | %8h |",
         $time, presetn, ptransfer, v1.pwrite, v1.paddr,
         v1.psel, v1.penable, v1.pwdata, v1.prdata);

    presetn = 1'b0;
	#4 presetn = 1'b1; //as active-low reset;
	#12 paddr_bus = 32'h1111_1111;ptransfer = 1'b1;pwdata_bus = 32'h1234_5678;pwrite_bus = 1'b1;
	#24 ptransfer = 1'b0;
    #40 ptransfer = 1'b1;pwrite_bus = 1'b0;paddr_bus = 32'h1111_1111;
    #55 ptransfer = 1'b0;
    #70 $finish;
end
endmodule

Testbench/vlsi.vcd
$date
	Fri Sep 25 23:26:06 2026
$end
$version
	Icarus Verilog
$end
$timescale
	1s
$end
$scope module Dut_tb $end
$var reg 32 ! paddr_bus [31:0] $end
$var reg 1 " pclk $end
$var reg 1 # presetn $end
$var reg 1 $ ptransfer $end
$var reg 32 % pwdata_bus [31:0] $end
$var reg 1 & pwrite_bus $end
$scope module v1 $end
$var wire 32 ' paddr_bus [31:0] $end
$var wire 1 " pclk $end
$var wire 1 ( pready $end
$var wire 1 # presetn $end
$var wire 1 $ ptransfer $end
$var wire 32 ) pwdata_bus [31:0] $end
$var wire 1 & pwrite_bus $end
$var wire 1 * pwrite $end
$var wire 32 + pwdata [31:0] $end
$var wire 1 , psel $end
$var wire 32 - prdata [31:0] $end
$var wire 1 . penable $end
$var wire 32 / paddr [31:0] $end
$scope module m1 $end
$var wire 32 0 paddr_bus [31:0] $end
$var wire 1 " pclk $end
$var wire 1 ( pready $end
$var wire 1 # presetn $end
$var wire 1 $ ptransfer $end
$var wire 32 1 pwdata_bus [31:0] $end
$var wire 1 & pwrite_bus $end
$var wire 32 2 prdata [31:0] $end
$var parameter 2 3 access $end
$var parameter 2 4 idle $end
$var parameter 2 5 setup $end
$var reg 2 6 ns [1:0] $end
$var reg 32 7 paddr [31:0] $end
$var reg 1 . penable $end
$var reg 2 8 ps [1:0] $end
$var reg 1 , psel $end
$var reg 32 9 pwdata [31:0] $end
$var reg 1 * pwrite $end
$upscope $end
$scope module s1 $end
$var wire 32 : paddr [31:0] $end
$var wire 1 " pclk $end
$var wire 1 . penable $end
$var wire 1 ( pready $end
$var wire 1 # presetn $end
$var wire 1 , psel $end
$var wire 32 ; pwdata [31:0] $end
$var wire 1 * pwrite $end
$var reg 32 < dataf [31:0] $end
$var reg 32 = prdata [31:0] $end
$upscope $end
$upscope $end
$upscope $end
$enddefinitions $end
$comment Show the parameter values. $end
$dumpall
b1 5
b0 4
b10 3
$end
#0
$dumpvars
bx =
b0 <
b0 ;
b0 :
b0 9
b0 8
b0 7
b0 6
bx 2
b0 1
b0 0
b0 /
0.
bx -
0,
b0 +
0*
b0 )
1(
b0 '
0&
b0 %
0$
0#
0"
b0 !
$end
#4
1#
#5
1"
#10
0"
#15
1"
#16
b1 6
b10010001101000101011001111000 +
b10010001101000101011001111000 9
b10010001101000101011001111000 ;
b10001000100010001000100010001 /
b10001000100010001000100010001 7
b10001000100010001000100010001 :
1*
1&
b10010001101000101011001111000 %
b10010001101000101011001111000 )
b10010001101000101011001111000 1
1$
b10001000100010001000100010001 !
b10001000100010001000100010001 '
b10001000100010001000100010001 0
#20
0"
#25
1,
b10 6
b1 8
1"
#30
0"
#35
b1 6
1.
1,
b10 8
1"
#40
1.
1,
b0 6
0"
0$
#45
0.
0,
b10010001101000101011001111000 <
b0 8
1"
#50
0"
#55
1"
#60
0"
#65
1"
#70
0"
#75
1"
#80
b1 6
0*
0"
0&
1$
#85
1,
b10 6
b1 8
1"
#90
0"
#95
b1 6
1.
1,
b10 8
1"
#100
0"
#105
b10 6
0.
1,
b10010001101000101011001111000 -
b10010001101000101011001111000 2
b10010001101000101011001111000 =
b1 8
1"
#110
0"
#115
b1 6
1.
1,
b10 8
1"
#120
0"
#125
b10 6
0.
1,
b1 8
1"
#130
0"
#135
1.
b10 8
1,
b0 6
1"
0$
#140
0"
#145
0.
0,
b0 8
1"
